django_separate_search/__init__.py
django_separate_search/admin.py
django_separate_search/apps.py
django_separate_search/utils.py
django_separate_search/templates/admin/custom_change_list.html
django_separate_search/templates/admin/custom_pagination.html
django_separate_search/templatetags/custom_paginator.py
django_better_search-0.2.0.dist-info/LICENSE.md
django_better_search-0.2.0.dist-info/METADATA
django_better_search-0.2.0.dist-info/WHEEL
django_better_search-0.2.0.dist-info/top_level.txt
django_better_search-0.2.0.dist-info/RECORD
