Metadata-Version: 2.1
Name: django-better-search
Version: 0.2.0
Summary: A different implementation of Django's admin search
Author-email: Shailesh Kumar <shailesh@eka.com>
Project-URL: Homepage, https://github.com/eka-care/django-better-search
Project-URL: Bug Tracker, https://github.com/eka-care/django-better-search/issues
Classifier: Development Status :: 3 - Alpha
Classifier: Programming Language :: Python :: 3
Classifier: Framework :: Django
Classifier: Intended Audience :: Developers
Classifier: License :: OSI Approved :: MIT License
Classifier: Operating System :: OS Independent
Requires-Python: >=3.7
License-File: LICENSE.md
